dtools/splitends/__init__.py
dtools/splitends/py.typed
dtools/splitends/splitend.py
dtools/splitends/splitend_node.py
dtools_splitends-0.29.0.dist-info/licenses/LICENSE
dtools_splitends-0.29.0.dist-info/WHEEL
dtools_splitends-0.29.0.dist-info/METADATA
dtools_splitends-0.29.0.dist-info/RECORD
